strictql_postgres/__init__.py
strictql_postgres/__main__.py
strictql_postgres/api.py
strictql_postgres/asyncpg_result_converter.py
strictql_postgres/code_generator.py
strictql_postgres/code_quality.py
strictql_postgres/common_types.py
strictql_postgres/complex_type_converter.py
strictql_postgres/config_generator.py
strictql_postgres/config_manager.py
strictql_postgres/dataclass_error.py
strictql_postgres/dir_diff.py
strictql_postgres/directory_reader.py
strictql_postgres/format_exception.py
strictql_postgres/generated_code_writer.py
strictql_postgres/meta_file.py
strictql_postgres/model_name_generator.py
strictql_postgres/pg_bind_params_type_getter.py
strictql_postgres/pg_response_schema_getter.py
strictql_postgres/py.typed
strictql_postgres/python_types.py
strictql_postgres/queries_generator.py
strictql_postgres/queries_to_generate.py
strictql_postgres/query_generator.py
strictql_postgres/string_in_snake_case.py
strictql_postgres/supported_postgres_types.py
strictql_postgres/type_str_creator.py
strictql_postgres/templates/__init__.py
strictql_postgres/templates/execute_with_params.txt
strictql_postgres/templates/execute_without_params.txt
strictql_postgres/templates/fetch_all_with_params.txt
strictql_postgres/templates/fetch_all_without_params.txt
strictql_postgres/templates/fetch_row_with_params.txt
strictql_postgres/templates/fetch_row_without_params.txt
strictql_postgres/templates/pydantic_model.txt
strictql_postgres-0.0.5.dist-info/METADATA
strictql_postgres-0.0.5.dist-info/WHEEL
strictql_postgres-0.0.5.dist-info/entry_points.txt
strictql_postgres-0.0.5.dist-info/licenses/LICENSE.txt
strictql_postgres-0.0.5.dist-info/RECORD
