Metadata-Version: 2.4
Name: strictql-postgres
Version: 0.0.5
Author-email: Bulygin Evgeny <tyztuz@gmail.com>
License-Expression: MIT
License-File: LICENSE.txt
Requires-Python: >=3.11
Requires-Dist: asyncpg<0.31.0,>=0.30
Requires-Dist: cyclopts<4.0.0,>=3.1.5
Requires-Dist: mako<2.0.0,>=1.3.9
Requires-Dist: pglast<8,>=7.3
Requires-Dist: pydantic<3.0.0,>=2.0.0
Requires-Dist: questionary<2.2.0,>=2.1.1
Requires-Dist: ruff<0.13,>=0.12.2
Requires-Dist: toml<0.10.3,>=0.10.2
Requires-Dist: types-toml
